.coveragerc
.travis.yml
LICENSE
MANIFEST.in
README.rst
setup.cfg
setup.py
tox.ini
Mopidy_Material_Webclient.egg-info/PKG-INFO
Mopidy_Material_Webclient.egg-info/SOURCES.txt
Mopidy_Material_Webclient.egg-info/dependency_links.txt
Mopidy_Material_Webclient.egg-info/entry_points.txt
Mopidy_Material_Webclient.egg-info/not-zip-safe
Mopidy_Material_Webclient.egg-info/requires.txt
Mopidy_Material_Webclient.egg-info/top_level.txt
mopidy_material_webclient/__init__.py
mopidy_material_webclient/ext.conf
mopidy_material_webclient/settingsspec.ini
mopidy_material_webclient/static/index.html
mopidy_material_webclient/static/css/angular-material.min.css
mopidy_material_webclient/static/css/app.min.css
mopidy_material_webclient/static/images/audio_mix.jpg
mopidy_material_webclient/static/partials/about.html
mopidy_material_webclient/static/partials/library.html
mopidy_material_webclient/static/partials/playlists.html
mopidy_material_webclient/static/partials/queue.html
mopidy_material_webclient/static/partials/search.html
mopidy_material_webclient/static/partials/settings.html
mopidy_material_webclient/static/partials/track-actions.html
mopidy_material_webclient/static/scripts/angular-animate.min.js
mopidy_material_webclient/static/scripts/angular-aria.min.js
mopidy_material_webclient/static/scripts/angular-material.min.js
mopidy_material_webclient/static/scripts/angular-route.min.js
mopidy_material_webclient/static/scripts/angular.min.js
mopidy_material_webclient/static/scripts/app.min.js
tests/__init__.py
tests/test_extension.py