Metadata-Version: 1.1
Name: Mopidy-Material-Webclient
Version: 0.2.1
Summary: A Mopidy web client with an Android Material feel
Home-page: https://github.com/matgallacher/mopidy-material-webclient
Author: Mat Gallacher
Author-email: mat.gallacher@gmail.com
License: Apache License, Version 2.0
Platform: UNKNOWN
Classifier: Environment :: No Input/Output (Daemon)
Classifier: Intended Audience :: End Users/Desktop
Classifier: License :: OSI Approved :: Apache Software License
Classifier: Operating System :: OS Independent
Classifier: Programming Language :: Python :: 2
Classifier: Topic :: Multimedia :: Sound/Audio :: Players
